neonpay/__init__.py
neonpay/_version.py
neonpay/analytics.py
neonpay/backup.py
neonpay/cli.py
neonpay/core.py
neonpay/errors.py
neonpay/event_collector.py
neonpay/factory.py
neonpay/middleware.py
neonpay/multi_bot_analytics.py
neonpay/notifications.py
neonpay/payments.py
neonpay/promotions.py
neonpay/py.typed
neonpay/security.py
neonpay/subscriptions.py
neonpay/sync.py
neonpay/templates.py
neonpay/utils.py
neonpay/web_analytics.py
neonpay/web_sync.py
neonpay/webhooks.py
neonpay/adapters/__init__.py
neonpay/adapters/aiogram_adapter.py
neonpay/adapters/base.py
neonpay/adapters/botapi_adapter.py
neonpay/adapters/ptb_adapter.py
neonpay/adapters/pyrogram_adapter.py
neonpay/adapters/raw_api_adapter.py
neonpay/adapters/telebot_adapter.py
neonpay-2.6.0.dist-info/licenses/LICENSE
neonpay-2.6.0.dist-info/METADATA
neonpay-2.6.0.dist-info/WHEEL
neonpay-2.6.0.dist-info/entry_points.txt
neonpay-2.6.0.dist-info/top_level.txt
neonpay-2.6.0.dist-info/RECORD
