Metadata-Version: 2.4
Name: neonpay
Version: 2.6.0
Summary: Modern Telegram Stars payment library with multi-bot support and enhanced security
Home-page: https://github.com/Abbasxan/neonpay
Author: Abbas Sultanov
Author-email: Abbas Sultanov <sultanov.abas@outlook.com>
Maintainer-email: Abbas Sultanov <sultanov.abas@outlook.com>
License: MIT
Project-URL: Homepage, https://github.com/Abbasxan/neonpay
Project-URL: Documentation, https://github.com/Abbasxan/neonpay#readme
Project-URL: Repository, https://github.com/Abbasxan/neonpay
Project-URL: Bug Tracker, https://github.com/Abbasxan/neonpay/issues
Project-URL: Security Policy, https://github.com/Abbasxan/neonpay/security/policy
Project-URL: Changelog, https://github.com/Abbasxan/neonpay/blob/main/CHANGELOG.md
Project-URL: Migration Guide, https://github.com/Abbasxan/neonpay/blob/main/docs/en/MIGRATION.md
Keywords: telegram,telegram-bot,payment,stars,xtr,crypto,pyrogram,aiogram,python-telegram-bot,telebot,webhook,security,validation,async,payment-processing
Classifier: Development Status :: 5 - Production/Stable
Classifier: Intended Audience :: Developers
Classifier: License :: OSI Approved :: MIT License
Classifier: Operating System :: OS Independent
Classifier: Programming Language :: Python :: 3
Classifier: Programming Language :: Python :: 3.9
Classifier: Programming Language :: Python :: 3.10
Classifier: Programming Language :: Python :: 3.11
Classifier: Programming Language :: Python :: 3.12
Classifier: Programming Language :: Python :: 3.13
Classifier: Topic :: Software Development :: Libraries :: Python Modules
Classifier: Topic :: Communications :: Chat
Classifier: Topic :: Office/Business :: Financial
Classifier: Topic :: Security
Classifier: Topic :: Internet :: WWW/HTTP :: HTTP Servers
Classifier: Topic :: Software Development :: Libraries :: Application Frameworks
Classifier: Framework :: AsyncIO
Classifier: Typing :: Typed
Requires-Python: >=3.9
License-File: LICENSE
Requires-Dist: aiohttp>=3.8.0
Requires-Dist: typing-extensions>=4.0.0
Requires-Dist: tgcrypto>=1.2.0
Provides-Extra: pyrogram
Requires-Dist: pyrogram>=2.0.0; extra == "pyrogram"
Requires-Dist: tgcrypto>=1.2.0; extra == "pyrogram"
Provides-Extra: aiogram
Requires-Dist: aiogram>=3.0.0; extra == "aiogram"
Provides-Extra: ptb
Requires-Dist: python-telegram-bot>=20.0; extra == "ptb"
Provides-Extra: telebot
Requires-Dist: pyTelegramBotAPI>=4.0.0; extra == "telebot"
Provides-Extra: raw
Requires-Dist: aiohttp>=3.8.0; extra == "raw"
Provides-Extra: sync
Requires-Dist: aiohttp>=3.8.0; extra == "sync"
Provides-Extra: web
Requires-Dist: aiohttp>=3.8.0; extra == "web"
Requires-Dist: aiofiles>=23.0.0; extra == "web"
Provides-Extra: all
Requires-Dist: pyrogram>=2.0.0; extra == "all"
Requires-Dist: tgcrypto>=1.2.0; extra == "all"
Requires-Dist: aiogram>=3.0.0; extra == "all"
Requires-Dist: python-telegram-bot>=20.0; extra == "all"
Requires-Dist: pyTelegramBotAPI>=4.0.0; extra == "all"
Requires-Dist: aiohttp>=3.8.0; extra == "all"
Requires-Dist: aiofiles>=23.0.0; extra == "all"
Provides-Extra: dev
Requires-Dist: pytest>=7.0.0; extra == "dev"
Requires-Dist: pytest-asyncio>=0.21.0; extra == "dev"
Requires-Dist: pytest-cov>=4.0.0; extra == "dev"
Requires-Dist: black>=23.0.0; extra == "dev"
Requires-Dist: isort>=5.12.0; extra == "dev"
Requires-Dist: mypy>=1.0.0; extra == "dev"
Requires-Dist: flake8>=6.0.0; extra == "dev"
Requires-Dist: pre-commit>=2.20.0; extra == "dev"
Requires-Dist: sphinx>=5.0.0; extra == "dev"
Requires-Dist: sphinx-rtd-theme>=1.0.0; extra == "dev"
Requires-Dist: ruff>=0.0.280; extra == "dev"
Dynamic: author
Dynamic: home-page
Dynamic: license-file
Dynamic: requires-python
